randovania_lupa/lua51_sr.cpython-310-x86_64-linux-gnu.so
randovania_lupa/lua51.cpython-310-x86_64-linux-gnu.so
randovania_lupa/__init__.py
randovania_lupa/lua51_dread.cpython-310-x86_64-linux-gnu.so
randovania_lupa/version.py
randovania_lupa-2.0.2.dist-info/top_level.txt
randovania_lupa-2.0.2.dist-info/RECORD
randovania_lupa-2.0.2.dist-info/LICENSE.txt
randovania_lupa-2.0.2.dist-info/METADATA
randovania_lupa-2.0.2.dist-info/WHEEL
