Metadata-Version: 2.1
Name: randovania-lupa
Version: 2.0.2
Summary: Python wrapper around Lua for usage in Randovania projects
Home-page: https://github.com/randovania/randovania-lupa
Author: Randovania
License: MIT style
Classifier: Development Status :: 5 - Production/Stable
Classifier: Intended Audience :: Developers
Classifier: Intended Audience :: Information Technology
Classifier: License :: OSI Approved :: MIT License
Classifier: Programming Language :: Cython
Classifier: Programming Language :: Python :: 3.10
Classifier: Programming Language :: Python :: 3.11
Classifier: Programming Language :: Python :: 3.12
Classifier: Programming Language :: Python :: 3.13
Classifier: Programming Language :: Lua
Classifier: Programming Language :: Other Scripting Engines
Classifier: Operating System :: OS Independent
Classifier: Topic :: Software Development
License-File: LICENSE.txt
